pytae/__init__.py
pytae/agg_df.py
pytae/other_utilities.py
pytae/plotting.py
pytae/qry.py
pytae/select.py
pytae/shape.py
pytae/.ipynb_checkpoints/__init__-checkpoint.py
pytae/.ipynb_checkpoints/agg_df-checkpoint.py
pytae/.ipynb_checkpoints/other_utilities-checkpoint.py
pytae/.ipynb_checkpoints/plotting-checkpoint.py
pytae/.ipynb_checkpoints/qry-checkpoint.py
pytae/.ipynb_checkpoints/select-checkpoint.py
pytae/.ipynb_checkpoints/shape-checkpoint.py
pytae/datasets/Untitled.ipynb
pytae/datasets/anagrams.parquet
pytae/datasets/anscombe.parquet
pytae/datasets/attention.parquet
pytae/datasets/brain_networks.parquet
pytae/datasets/car_crashes.parquet
pytae/datasets/diamonds.parquet
pytae/datasets/dots.parquet
pytae/datasets/dowjones.parquet
pytae/datasets/exercise.parquet
pytae/datasets/flights.parquet
pytae/datasets/fmri.parquet
pytae/datasets/geyser.parquet
pytae/datasets/glue.parquet
pytae/datasets/healthexp.parquet
pytae/datasets/iris.parquet
pytae/datasets/mpg.parquet
pytae/datasets/penguins.parquet
pytae/datasets/planets.parquet
pytae/datasets/seaice.parquet
pytae/datasets/taxis.parquet
pytae/datasets/tips.parquet
pytae/datasets/titanic.parquet
pytae/datasets/.ipynb_checkpoints/Untitled-checkpoint.ipynb
pytae-2.6.1.dist-info/METADATA
pytae-2.6.1.dist-info/WHEEL
pytae-2.6.1.dist-info/licenses/LICENSE
pytae-2.6.1.dist-info/RECORD
