Metadata-Version: 2.4
Name: pytae
Version: 2.6.1
Dynamic: Requires-Dist
Summary: A package to enhance common day to day tasks in the life of a data scientist
Project-URL: Homepage, https://github.com/maddytae/pytae
Project-URL: Bug Tracker, https://github.com/maddytae/pytae/issues
Author-email: Madhukar Kumar Jha <madhukar.k.jha@gmail.com>
License-File: LICENSE
Classifier: License :: OSI Approved :: MIT License
Classifier: Operating System :: OS Independent
Classifier: Programming Language :: Python :: 3
Requires-Python: >=3.7
